[
  {
    "keyword": "Feature",
    "name": "Menu",
    "line": 2,
    "id": "menu",
    "tags": [
      {
        "name": "@all",
        "line": 1
      }
    ],
    "uri": "test\\features\\menu.feature",
    "elements": [
      {
        "id": "menu;verify-user-can-open-menu",
        "keyword": "Scenario",
        "line": 5,
        "name": "Verify user can open menu",
        "tags": [
          {
            "name": "@all",
            "line": 1
          },
          {
            "name": "@epam",
            "line": 4
          }
        ],
        "type": "scenario",
        "steps": [
          {
            "arguments": [],
            "keyword": "Given ",
            "line": 6,
            "name": "I open \"https://www.epam.com/\" url",
            "match": {
              "location": "test\\step_definitions\\actionSteps\\browserInteractions.js:11"
            },
            "result": {
              "status": "passed",
              "duration": 6065000000
            }
          },
          {
            "arguments": [],
            "keyword": "When ",
            "line": 7,
            "name": "I wait until \"Menu\" is present",
            "match": {
              "location": "test\\step_definitions\\actionSteps\\waiters.js:9"
            },
            "result": {
              "status": "passed",
              "duration": 20000000
            }
          },
          {
            "arguments": [],
            "keyword": "Then ",
            "line": 8,
            "name": "Text of \"Menu\" should contain \"MENU\"",
            "match": {
              "location": "test\\step_definitions\\validationSteps\\validationSteps.js:30"
            },
            "result": {
              "status": "passed",
              "duration": 17000000
            }
          },
          {
            "arguments": [],
            "keyword": "When ",
            "line": 10,
            "name": "I click \"Menu\"",
            "match": {
              "location": "test\\step_definitions\\actionSteps\\mouseInteractions.js:6"
            },
            "result": {
              "status": "passed",
              "duration": 65000000
            }
          },
          {
            "arguments": [],
            "keyword": "And ",
            "line": 11,
            "name": "I wait until \"Expanded Menu\" is present",
            "match": {
              "location": "test\\step_definitions\\actionSteps\\waiters.js:9"
            },
            "result": {
              "status": "passed",
              "duration": 23000000
            }
          },
          {
            "arguments": [],
            "keyword": "Then ",
            "line": 12,
            "name": "\"Expanded Menu\" should be visible",
            "match": {
              "location": "test\\step_definitions\\validationSteps\\validationSteps.js:8"
            },
            "result": {
              "status": "passed",
              "duration": 10000000
            }
          },
          {
            "arguments": [],
            "keyword": "And ",
            "line": 13,
            "name": "Count of \"Expanded Menu Sublists\" should not be \"3\"",
            "match": {
              "location": "test\\step_definitions\\validationSteps\\validationSteps.js:16"
            },
            "result": {
              "status": "passed",
              "duration": 13000000
            }
          },
          {
            "arguments": [],
            "keyword": "And ",
            "line": 14,
            "name": "Text of \"Expanded Menu Row Titles\" should contain \"HOW WE DO IT\"",
            "match": {
              "location": "test\\step_definitions\\validationSteps\\validationSteps.js:30"
            },
            "result": {
              "status": "passed",
              "duration": 76000000
            }
          },
          {
            "arguments": [],
            "keyword": "And ",
            "line": 15,
            "name": "Count of \"Expanded Menu Row Titles\" should be \"6\"",
            "match": {
              "location": "test\\step_definitions\\validationSteps\\validationSteps.js:16"
            },
            "result": {
              "status": "passed",
              "duration": 5000000
            }
          },
          {
            "arguments": [],
            "keyword": "And ",
            "line": 16,
            "name": "I wait \"1\" seconds",
            "match": {
              "location": "test\\step_definitions\\actionSteps\\browserInteractions.js:6"
            },
            "result": {
              "status": "passed",
              "duration": 1004000000
            }
          },
          {
            "keyword": "After",
            "hidden": true,
            "match": {
              "location": "test\\step_definitions\\hooks.js:6"
            },
            "result": {
              "status": "passed",
              "duration": 1000000
            }
          },
          {
            "keyword": "After",
            "hidden": true,
            "match": {
              "location": "node_modules\\protractor-cucumber-framework\\lib\\resultsCapturer.js:27"
            },
            "result": {
              "status": "passed",
              "duration": 1000000
            }
          }
        ]
      }
    ]
  }
]